ai_agent/__init__.py
ai_agent/app.py
ai_agent/constants.py
ai_agent/sample.py
ai_agent/settings.py
ai_controller-0.1.0.dist-info/METADATA
ai_controller-0.1.0.dist-info/WHEEL
ai_controller-0.1.0.dist-info/top_level.txt
ai_controller-0.1.0.dist-info/RECORD
