Metadata-Version: 2.1
Name: ai-controller
Version: 0.1.0
Summary: AI-Agent (Auto-Code Executor) is a Python module that dynamically executes Python functions based on textual input. It leverages a language model (LLM) to match the input text with function descriptions and then executes the corresponding function from a specified file.
Home-page: https://github.com/Tanay-Sharma-01/ai_controller/tree/develop
Author: Tanay Sharma
Author-email: tanaysharmaajmer@gmail.com
License: UNKNOWN
Platform: UNKNOWN
Classifier: Programming Language :: Python :: 3
Classifier: License :: OSI Approved :: MIT License
Classifier: Operating System :: OS Independent
Requires-Python: >3.10
